<?xml version="1.0" encoding="UTF-8" standalone="no"?><NamedEntities><Entity type="landmark"><Name>Annual average daily traffic</Name><Name>Utah State Route 68#cite note-AADT-2007-2</Name><Name>Utah State Route 68#cite note-AADT-2000-3</Name><Name>indexphp?title=Utah State Route 68&amp;action=edit&amp;section=2</Name><Name>Elberta</Name><Name>US-6</Name><Name>Utah County</Name><Name>Utah Lake</Name><Name>Planned community</Name><Name>Mosida</Name><Name>Saratoga Springs</Name><Name>SR-73</Name><Name>Lehi</Name><Name>Eagle Mountain</Name><Name>Camp Williams</Name><Name>Utah State Route 68#cite note-googlemaps-4</Name><Name>indexphp?title=Utah State Route 68&amp;action=edit&amp;section=3</Name><Name>North Salt Lake</Name><Name>Salt Lake County</Name><Name>Salt Lake City metropolitan area</Name><Name>Wasatch Front</Name><Name>Traverse Mountains</Name><Name>Utah State Route 68#cite note-UHE-5</Name><Name>Denver and Rio Grande Western Railroad</Name><Name>Interstate 15 in Utah</Name><Name>Utah State Route 68#cite note-googlemaps-4</Name><Name>Bluffdale</Name><Name>Utah State Route 140</Name><Name>Utah State Prison</Name><Name>Utah State Route 154</Name><Name>Riverton</Name><Name>Utah State Route 71</Name><Name>South Jordan</Name><Name>Utah State Route 175</Name><Name>Utah State Route 151</Name><Name>Utah State Route 209</Name><Name>West Jordan</Name><Name>Utah State Route 68#cite note-googlemaps-4</Name><Name>Taylorsville</Name><Name>Interstate 215 (Utah)</Name><Name>Salt Lake Community College</Name><Name>West Valley City</Name><Name>Single-point urban interchange</Name><Name>Utah State Route 201</Name><Name>Salt Lake City</Name><Name>Jordan River (Utah)</Name><Name>Glendale, Salt Lake City</Name><Name>Poplar Grove, Salt Lake City</Name><Name>Interstate 80 (Utah)</Name><Name>Salt Lake City International Airport</Name><Name>Rose Park, Salt Lake City</Name><Name>Utah State Route 68#cite note-googlemaps-4</Name><Name>indexphp?title=Utah State Route 68&amp;action=edit&amp;section=4</Name><Name>Davis County</Name><Name>North Salt Lake</Name><Name>Skypark Airport</Name><Name>Bountiful</Name><Name>Utah State Route 68#cite note-googlemaps-4</Name></Entity></NamedEntities>